mcp_mermaid_converter-0.2.1.dist-info/licenses/LICENSE
mcp_mermaid_server/__init__.py
mcp_mermaid_server/__main__.py
mcp_mermaid_server/converter.py
mcp_mermaid_server/exceptions.py
mcp_mermaid_server/logger.py
mcp_mermaid_server/py.typed
mcp_mermaid_server/server.py
mcp_mermaid_converter-0.2.1.dist-info/METADATA
mcp_mermaid_converter-0.2.1.dist-info/WHEEL
mcp_mermaid_converter-0.2.1.dist-info/entry_points.txt
mcp_mermaid_converter-0.2.1.dist-info/top_level.txt
mcp_mermaid_converter-0.2.1.dist-info/RECORD
