Metadata-Version: 2.4
Name: mcp-mermaid-converter
Version: 0.2.1
Summary: 将Mermaid图表转换为PNG或SVG图片的MCP服务（基于FastMCP）
Author-email: MCP Mermaid Converter Team <your-email@example.com>
License-Expression: MIT
Project-URL: Homepage, https://github.com/yourusername/mcp-mermaid-converter
Project-URL: Repository, https://github.com/yourusername/mcp-mermaid-converter
Project-URL: Bug Tracker, https://github.com/yourusername/mcp-mermaid-converter/issues
Keywords: mermaid,diagram,converter,visualization,kroki,mcp,fastmcp,model-context-protocol
Classifier: Development Status :: 4 - Beta
Classifier: Intended Audience :: Developers
Classifier: Operating System :: OS Independent
Classifier: Programming Language :: Python :: 3
Classifier: Programming Language :: Python :: 3.10
Classifier: Programming Language :: Python :: 3.11
Classifier: Programming Language :: Python :: 3.12
Classifier: Topic :: Software Development :: Libraries :: Python Modules
Classifier: Topic :: Multimedia :: Graphics :: Graphics Conversion
Requires-Python: >=3.10
License-File: LICENSE
Requires-Dist: fastmcp>=0.1.0
Requires-Dist: httpx>=0.25.0
Requires-Dist: pydantic>=2.0.0
Provides-Extra: dev
Requires-Dist: pytest>=7.0.0; extra == "dev"
Requires-Dist: pytest-asyncio>=0.21.0; extra == "dev"
Requires-Dist: pytest-cov>=4.0.0; extra == "dev"
Requires-Dist: black>=23.0.0; extra == "dev"
Requires-Dist: ruff>=0.1.0; extra == "dev"
Requires-Dist: mypy>=1.0.0; extra == "dev"
Requires-Dist: types-httpx>=0.25.0; extra == "dev"
Dynamic: license-file
